jupyter_utils_tddschn/__init__.py
jupyter_utils_tddschn/notebook_importer.py
jupyter_utils_tddschn/notebook_shower.py
jupyter_utils_tddschn-0.1.6.dist-info/LICENSE
jupyter_utils_tddschn-0.1.6.dist-info/WHEEL
jupyter_utils_tddschn-0.1.6.dist-info/METADATA
jupyter_utils_tddschn-0.1.6.dist-info/RECORD
